{
    "dataFormat": "json",
    "datasource": {
        "chart": {
            "caption": "AT&T Share Prices",
            "declinethickness": "1",
            "numberprefix": "$",
            "rallythickness": "3",
            "reversalpercentage": "4",
            "rotatelabels": "1",
            "showanchors": "0",
            "showborder": "0",
            "showvalues": "0",
            "subcaption": "(September - November 2009)"
        },
        "data": [
            {
                "label": "9/2",
                "value": "24.99"
            },
            {
                "label": "9/3",
                "value": "24.77"
            },
            {
                "label": "9/4",
                "value": "25.12"
            },
            {
                "label": "9/8",
                "value": "25.36"
            },
            {
                "label": "9/9",
                "value": "25.55"
            },
            {
                "label": "9/10",
                "value": "26.16"
            },
            {
                "label": "9/11",
                "value": "26.26"
            },
            {
                "label": "9/14",
                "value": "26.13"
            },
            {
                "label": "9/15",
                "value": "26.3"
            },
            {
                "label": "9/16",
                "value": "26.14"
            },
            {
                "label": "9/17",
                "value": "25.97"
            },
            {
                "label": "9/18",
                "value": "26.64"
            },
            {
                "label": "9/21",
                "value": "26.46"
            },
            {
                "label": "9/22",
                "value": "26.1"
            },
            {
                "label": "9/23",
                "value": "26.72"
            },
            {
                "label": "9/24",
                "value": "26.62"
            },
            {
                "label": "9/25",
                "value": "26.55"
            },
            {
                "label": "9/28",
                "value": "27.02"
            },
            {
                "label": "9/29",
                "value": "26.79"
            },
            {
                "label": "9/30",
                "value": "26.6"
            },
            {
                "label": "10/1",
                "value": "26.21"
            },
            {
                "label": "10/2",
                "value": "26.12"
            },
            {
                "label": "10/5",
                "value": "26.36"
            },
            {
                "label": "10/6",
                "value": "26.74"
            },
            {
                "label": "10/7",
                "value": "26.18"
            },
            {
                "label": "10/9",
                "value": "25.66"
            },
            {
                "label": "10/12",
                "value": "25.6"
            },
            {
                "label": "10/14",
                "value": "25.83"
            },
            {
                "label": "10/15",
                "value": "25.91"
            },
            {
                "label": "10/23",
                "value": "25.73"
            },
            {
                "label": "10/27",
                "value": "25.6"
            },
            {
                "label": "10/28",
                "value": "26.08"
            },
            {
                "label": "10/29",
                "value": "26.23"
            },
            {
                "label": "10/30",
                "value": "25.67"
            },
            {
                "label": "11/2",
                "value": "25.59"
            },
            {
                "label": "11/3",
                "value": "25.36"
            },
            {
                "label": "11/4",
                "value": "25.53"
            },
            {
                "label": "11/5",
                "value": "25.96"
            },
            {
                "label": "11/9",
                "value": "26.34"
            },
            {
                "label": "11/10",
                "value": "26.36"
            },
            {
                "label": "11/11",
                "value": "26.44"
            },
            {
                "label": "11/12",
                "value": "26.29"
            },
            {
                "label": "11/20",
                "value": "26.02"
            },
            {
                "label": "11/23",
                "value": "26.78"
            },
            {
                "label": "11/25",
                "value": "27.08"
            },
            {
                "label": "11/30",
                "value": "26.94"
            },
            {
                "label": "11/16",
                "value": "26.29"
            },
            {
                "label": "10/29",
                "value": "26.23"
            },
            {
                "label": "11/5",
                "value": "25.06"
            },
            {
                "label": "9/2",
                "value": "25.99"
            }
        ]
    },
    "height": "600",
    "type": "kagi",
    "width": "800"
}